LICENSE
README.md
pyproject.toml
setup.py
flipkart_miraie_ac/__init__.py
flipkart_miraie_ac/broker.py
flipkart_miraie_ac/constants.py
flipkart_miraie_ac/device.py
flipkart_miraie_ac/enums.py
flipkart_miraie_ac/home.py
flipkart_miraie_ac/hub.py
flipkart_miraie_ac/logger.py
flipkart_miraie_ac/topic.py
flipkart_miraie_ac/user.py
flipkart_miraie_ac/utils.py
flipkart_miraie_ac.egg-info/PKG-INFO
flipkart_miraie_ac.egg-info/SOURCES.txt
flipkart_miraie_ac.egg-info/dependency_links.txt
flipkart_miraie_ac.egg-info/top_level.txt