Metadata-Version: 2.1
Name: flipkart-miraie-ac
Version: 0.0.1
Summary: Flipkart-MirAIe-AC API for Python
Home-page: https://github.com/yourusername/my_package
Author: Pratik Bhoir
Author-email: pratbhoir@gmail.com
Classifier: Programming Language :: Python :: 3
Classifier: License :: OSI Approved :: MIT License
Classifier: Operating System :: OS Independent
Requires-Python: >=3.6
License-File: LICENSE
